neon_llm_core/__init__.py
neon_llm_core/chatbot.py
neon_llm_core/llm.py
neon_llm_core/rmq.py
neon_llm_core/utils/__init__.py
neon_llm_core/utils/config.py
neon_llm_core/utils/constants.py
neon_llm_core/utils/personas/__init__.py
neon_llm_core/utils/personas/models.py
neon_llm_core/utils/personas/provider.py
neon_llm_core/utils/personas/state.py
tests/__init__.py
tests/test_chatbot.py
tests/test_llm.py
tests/test_rmq.py
tests/test_utils/__init__.py
tests/test_utils/test_provider.py
tests/test_utils/test_state.py
tests/test_utils/utils/__init__.py
tests/test_utils/utils/factory.py
neon_llm_core-0.2.0.dist-info/LICENSE.md
neon_llm_core-0.2.0.dist-info/METADATA
neon_llm_core-0.2.0.dist-info/WHEEL
neon_llm_core-0.2.0.dist-info/top_level.txt
neon_llm_core-0.2.0.dist-info/zip-safe
neon_llm_core-0.2.0.dist-info/RECORD
