Metadata-Version: 2.1
Name: neon-llm-core
Version: 0.2.0
Summary: Core Neon LLM service
Home-page: https://github.com/NeonGeckoCom/neon-llm-core
Author: NeonGecko
Author-email: developers@neon.ai
License: BSD-3.0
Classifier: Intended Audience :: Developers
Classifier: Programming Language :: Python :: 3.6
License-File: LICENSE.md
Requires-Dist: neon-mq-connector~=0.9
Requires-Dist: neon-utils[sentry]~=1.12
Requires-Dist: ovos-config>=0.0.10,~=0.0
Requires-Dist: pydantic~=2.6
Requires-Dist: neon-data-models~=0.0
Provides-Extra: chatbots
Requires-Dist: neon-chatbot-core~=2.4; extra == "chatbots"
Provides-Extra: test
Requires-Dist: pytest; extra == "test"
Requires-Dist: pytest-rabbitmq; extra == "test"
